qairt_visualizer/__init__.py
qairt_visualizer/apis.py
qairt_visualizer/core/__init__.py
qairt_visualizer/core/errors.py
qairt_visualizer/core/visualizer_service.py
qairt_visualizer/core/communicators/__init__.py
qairt_visualizer/core/communicators/base_communicator_context.py
qairt_visualizer/core/communicators/electron_communicator_context.py
qairt_visualizer/core/communicators/factory_communicator.py
qairt_visualizer/core/communicators/web_communicator_context.py
qairt_visualizer/core/helpers/version.py
qairt_visualizer/core/launchers/__init__.py
qairt_visualizer/core/launchers/base_ui_launcher_context.py
qairt_visualizer/core/launchers/electron_launcher_context.py
qairt_visualizer/core/launchers/factory_ui_launcher.py
qairt_visualizer/core/launchers/web_launcher_context.py
qairt_visualizer/core/launchers/models/process_attributes.py
qairt_visualizer/core/modules/report_generator/report_generator.py
qairt_visualizer/core/modules/report_generator/models/report_header.py
qairt_visualizer/core/parsers/dlc_parser/dlc_parser.py
qairt_visualizer/core/parsers/dlc_parser/get_source_topology.py
qairt_visualizer/core/parsers/dlc_parser/libDlModelToolsPy.pyd
qairt_visualizer/core/parsers/dlc_parser/libDlModelToolsPy.so
qairt_visualizer/core/parsers/dlc_parser/libPyIrGraph.pyd
qairt_visualizer/core/parsers/dlc_parser/libPyIrGraph.so
qairt_visualizer/core/parsers/dlc_parser/op_tensor_parser.py
qairt_visualizer/core/parsers/dlc_parser/helpers/exception_helpers.py
qairt_visualizer/core/parsers/dlc_parser/models/op_tensor_mappings.py
qairt_visualizer/core/ui/__init__.py
qairt_visualizer/core/ui/ui_runner.py
qairt_visualizer/core/ui/visualizer_web_server.py
qairt_visualizer/core/ui/contexts/__init__.py
qairt_visualizer/core/ui/contexts/autoshutdown_context.py
qairt_visualizer/core/ui/dist/qairt_visualizer
qairt_visualizer/core/ui/dist/browser/__init__.py
qairt_visualizer/core/ui/dist/browser/acuity-metadata.json
qairt_visualizer/core/ui/dist/browser/acuity.js
qairt_visualizer-0.7.0.dist-info/LICENSE.pdf
qairt_visualizer-0.7.0.dist-info/METADATA
qairt_visualizer-0.7.0.dist-info/WHEEL
qairt_visualizer-0.7.0.dist-info/entry_points.txt
qairt_visualizer-0.7.0.dist-info/top_level.txt
qairt_visualizer-0.7.0.dist-info/RECORD
