Metadata-Version: 2.2
Name: qairt-visualizer
Version: 0.7.0
Summary: Qualcomm AI Runtime visualization application for AI models and runtime metrics.
Author-email: "Qualcomm Innovation Center, Inc." <quic.opensource@quicinc.com>
Maintainer-email: qairt-visualizer-support <qairt.visualizer.support@quicinc.com>
License: Proprietary
Classifier: Development Status :: 4 - Beta
Classifier: Intended Audience :: Developers
Classifier: Operating System :: MacOS :: MacOS X
Classifier: Operating System :: Microsoft :: Windows :: Windows 10
Classifier: Operating System :: POSIX :: Linux
Classifier: Programming Language :: Python :: 3.10
Classifier: Programming Language :: Python :: 3.11
Classifier: Programming Language :: Python :: 3.12
Classifier: Programming Language :: Python :: 3.13
Classifier: Topic :: Scientific/Engineering
Classifier: Topic :: Scientific/Engineering :: Artificial Intelligence
Classifier: Topic :: Scientific/Engineering :: Visualization
Classifier: Topic :: Software Development
Requires-Python: >=3.10
License-File: LICENSE.pdf
Requires-Dist: aiohttp<4.0.0,>=3.10.10
Requires-Dist: chardet<6.0.0,>=5.2.0
Requires-Dist: click<9.0.0,>=8.1.8
Requires-Dist: concurrent-log-handler<1.0.0,>=0.9.25
Requires-Dist: fastapi<1.0.0,>=0.115.4
Requires-Dist: ipython<9.0.0,>=8.29.0
Requires-Dist: psutil<7.0.0,>=6.1.0
Requires-Dist: pydantic<2.8.0,>=2.7.4
Requires-Dist: python-socketio<6.0.0,>=5.11.4
Requires-Dist: pyzmq<27.0.0,>=26.2.0
Requires-Dist: requests<3.0.0,>=2.32.3
Requires-Dist: uvicorn<1.0.0,>=0.32.0
